{"match_id":"f3f84561-7105-4c91-a478-8ba4c0c7b816","map_id":"Lockdown","date":"February_10","duration_ms":407,"human_count":1,"bot_count":0,"players":{"6c16352d-1a74-4cbc-83b1-6cf5cad847cf":{"is_bot":false,"events":[{"t":0,"x":156.3,"y":374.8,"e":"Position"},{"t":15,"x":158.7,"y":374.3,"e":"Position"},{"t":20,"x":166.9,"y":381.5,"e":"Position"},{"t":25,"x":175.9,"y":406.5,"e":"Position"},{"t":30,"x":186.6,"y":408.5,"e":"Position"},{"t":40,"x":193.7,"y":408.1,"e":"Position"},{"t":45,"x":197.6,"y":399.5,"e":"Position"},{"t":50,"x":196.0,"y":387.7,"e":"Position"},{"t":51,"x":195.4,"y":387.8,"e":"Loot"},{"t":60,"x":199.3,"y":384.0,"e":"Position"},{"t":69,"x":199.3,"y":384.0,"e":"Loot"},{"t":70,"x":197.4,"y":384.3,"e":"Position"},{"t":75,"x":196.6,"y":381.4,"e":"Position"},{"t":83,"x":198.8,"y":383.1,"e":"Loot"},{"t":85,"x":197.0,"y":386.8,"e":"Position"},{"t":96,"x":207.3,"y":383.8,"e":"Position"},{"t":100,"x":209.4,"y":374.9,"e":"Loot"},{"t":101,"x":209.4,"y":374.7,"e":"Position"},{"t":106,"x":211.4,"y":373.7,"e":"Position"},{"t":121,"x":215.8,"y":375.7,"e":"Position"},{"t":123,"x":216.3,"y":374.0,"e":"Loot"},{"t":126,"x":221.9,"y":377.9,"e":"Position"},{"t":131,"x":213.0,"y":376.2,"e":"Loot"},{"t":131,"x":213.0,"y":376.2,"e":"Position"},{"t":136,"x":208.9,"y":369.8,"e":"Position"},{"t":141,"x":200.5,"y":378.3,"e":"Position"},{"t":146,"x":209.6,"y":398.8,"e":"Position"},{"t":150,"x":216.5,"y":396.1,"e":"Loot"},{"t":151,"x":216.7,"y":397.3,"e":"Position"},{"t":156,"x":212.4,"y":390.3,"e":"Position"},{"t":161,"x":197.9,"y":418.5,"e":"Position"},{"t":166,"x":202.9,"y":416.6,"e":"Position"},{"t":171,"x":218.3,"y":429.2,"e":"Position"},{"t":176,"x":238.7,"y":418.0,"e":"Position"},{"t":181,"x":267.6,"y":411.8,"e":"Position"},{"t":186,"x":290.8,"y":429.8,"e":"Position"},{"t":191,"x":301.9,"y":452.4,"e":"Position"},{"t":196,"x":301.9,"y":474.5,"e":"Position"},{"t":201,"x":316.9,"y":481.2,"e":"Position"},{"t":206,"x":324.1,"y":499.8,"e":"Position"},{"t":211,"x":326.5,"y":507.8,"e":"Position"},{"t":216,"x":348.7,"y":493.8,"e":"Position"},{"t":221,"x":365.2,"y":480.7,"e":"Position"},{"t":226,"x":368.1,"y":467.5,"e":"Loot"},{"t":226,"x":367.5,"y":467.7,"e":"Position"},{"t":231,"x":363.5,"y":461.7,"e":"Position"},{"t":231,"x":363.5,"y":461.7,"e":"Loot"},{"t":236,"x":367.2,"y":458.1,"e":"Position"},{"t":241,"x":377.0,"y":469.0,"e":"Position"},{"t":245,"x":375.2,"y":469.3,"e":"Loot"},{"t":251,"x":365.3,"y":478.4,"e":"Position"},{"t":261,"x":357.5,"y":475.0,"e":"Position"},{"t":272,"x":356.9,"y":477.5,"e":"Position"},{"t":273,"x":359.0,"y":480.8,"e":"BotKill"},{"t":277,"x":370.0,"y":477.7,"e":"Position"},{"t":282,"x":375.3,"y":476.7,"e":"Position"},{"t":284,"x":376.7,"y":476.9,"e":"Loot"},{"t":284,"x":376.7,"y":476.9,"e":"Loot"},{"t":287,"x":378.1,"y":471.1,"e":"Position"},{"t":292,"x":370.3,"y":459.1,"e":"Position"},{"t":297,"x":361.3,"y":461.1,"e":"Position"},{"t":302,"x":352.3,"y":458.6,"e":"Position"},{"t":307,"x":373.1,"y":445.8,"e":"Position"},{"t":312,"x":384.1,"y":441.5,"e":"Position"},{"t":314,"x":392.2,"y":444.2,"e":"Loot"},{"t":317,"x":388.0,"y":452.8,"e":"Position"},{"t":327,"x":383.8,"y":441.9,"e":"Position"},{"t":327,"x":383.5,"y":441.4,"e":"Loot"},{"t":330,"x":379.6,"y":443.0,"e":"Loot"},{"t":332,"x":371.5,"y":447.3,"e":"Position"},{"t":337,"x":353.7,"y":455.7,"e":"Position"},{"t":342,"x":333.4,"y":468.1,"e":"Position"},{"t":347,"x":332.8,"y":467.8,"e":"Position"},{"t":352,"x":333.8,"y":468.2,"e":"Position"},{"t":357,"x":337.5,"y":460.2,"e":"Position"},{"t":362,"x":349.0,"y":439.6,"e":"Position"},{"t":367,"x":363.0,"y":443.3,"e":"Position"},{"t":372,"x":377.3,"y":447.9,"e":"Position"},{"t":377,"x":387.3,"y":455.4,"e":"Position"},{"t":382,"x":419.1,"y":451.3,"e":"Position"},{"t":387,"x":434.5,"y":452.5,"e":"Position"},{"t":392,"x":428.8,"y":441.1,"e":"Position"},{"t":397,"x":425.0,"y":442.3,"e":"Position"},{"t":402,"x":433.6,"y":455.8,"e":"Position"},{"t":407,"x":436.2,"y":462.8,"e":"Position"}]}}}