{"match_id":"ea5066c9-ddd7-41e1-b73a-6a32c07f06f1","map_id":"AmbroseValley","date":"February_10","duration_ms":699,"human_count":1,"bot_count":0,"players":{"c50d5659-4761-4c86-b513-e371d8f1d8a6":{"is_bot":false,"events":[{"t":0,"x":254.4,"y":705.4,"e":"Position"},{"t":10,"x":261.7,"y":694.7,"e":"Position"},{"t":15,"x":259.8,"y":696.1,"e":"Loot"},{"t":15,"x":259.8,"y":696.1,"e":"Position"},{"t":21,"x":257.4,"y":677.3,"e":"Position"},{"t":26,"x":257.3,"y":678.7,"e":"Position"},{"t":31,"x":277.6,"y":684.5,"e":"Position"},{"t":36,"x":306.3,"y":701.3,"e":"Position"},{"t":37,"x":306.4,"y":701.3,"e":"Loot"},{"t":41,"x":325.9,"y":697.0,"e":"Position"},{"t":46,"x":330.7,"y":662.9,"e":"Position"},{"t":49,"x":328.0,"y":660.1,"e":"Loot"},{"t":51,"x":323.8,"y":658.6,"e":"Position"},{"t":56,"x":335.5,"y":663.6,"e":"Position"},{"t":58,"x":335.5,"y":663.6,"e":"Loot"},{"t":66,"x":331.6,"y":675.6,"e":"Position"},{"t":71,"x":329.6,"y":678.9,"e":"Position"},{"t":76,"x":350.8,"y":704.5,"e":"Position"},{"t":80,"x":359.4,"y":708.9,"e":"Loot"},{"t":81,"x":359.4,"y":708.9,"e":"Position"},{"t":86,"x":355.0,"y":724.4,"e":"Position"},{"t":91,"x":359.0,"y":760.3,"e":"Position"},{"t":96,"x":387.7,"y":771.2,"e":"Position"},{"t":101,"x":402.1,"y":796.2,"e":"Position"},{"t":104,"x":400.6,"y":802.3,"e":"Loot"},{"t":106,"x":402.0,"y":804.3,"e":"Position"},{"t":111,"x":406.9,"y":807.4,"e":"Position"},{"t":116,"x":413.9,"y":811.0,"e":"Position"},{"t":117,"x":413.9,"y":811.0,"e":"Loot"},{"t":121,"x":414.6,"y":806.1,"e":"Position"},{"t":122,"x":417.6,"y":805.3,"e":"Loot"},{"t":126,"x":421.5,"y":805.2,"e":"Loot"},{"t":126,"x":421.5,"y":805.2,"e":"Position"},{"t":131,"x":411.9,"y":812.6,"e":"Position"},{"t":136,"x":408.3,"y":833.4,"e":"Position"},{"t":141,"x":390.1,"y":859.6,"e":"Position"},{"t":146,"x":382.7,"y":894.5,"e":"Position"},{"t":151,"x":382.9,"y":908.9,"e":"Position"},{"t":166,"x":371.6,"y":906.0,"e":"Position"},{"t":171,"x":370.8,"y":889.9,"e":"Position"},{"t":176,"x":368.2,"y":889.3,"e":"Position"},{"t":181,"x":378.8,"y":888.7,"e":"Position"},{"t":191,"x":374.5,"y":894.9,"e":"Loot"},{"t":191,"x":374.5,"y":894.9,"e":"Loot"},{"t":191,"x":373.9,"y":894.8,"e":"Position"},{"t":192,"x":372.8,"y":894.7,"e":"Loot"},{"t":202,"x":366.6,"y":882.1,"e":"Position"},{"t":207,"x":363.9,"y":882.6,"e":"Position"},{"t":212,"x":350.8,"y":901.0,"e":"Position"},{"t":217,"x":317.4,"y":894.9,"e":"Position"},{"t":222,"x":281.9,"y":904.2,"e":"Position"},{"t":227,"x":254.5,"y":885.8,"e":"Position"},{"t":232,"x":242.6,"y":873.1,"e":"Position"},{"t":237,"x":224.3,"y":867.4,"e":"Position"},{"t":240,"x":224.6,"y":874.5,"e":"Loot"},{"t":240,"x":224.6,"y":874.5,"e":"Loot"},{"t":242,"x":224.6,"y":874.5,"e":"Position"},{"t":247,"x":222.0,"y":867.9,"e":"Position"},{"t":252,"x":193.2,"y":878.2,"e":"Position"},{"t":257,"x":157.4,"y":883.7,"e":"Position"},{"t":262,"x":127.7,"y":879.0,"e":"Position"},{"t":267,"x":129.3,"y":874.0,"e":"Position"},{"t":272,"x":144.4,"y":842.9,"e":"Position"},{"t":277,"x":177.4,"y":825.5,"e":"Position"},{"t":282,"x":189.3,"y":778.4,"e":"Position"},{"t":287,"x":194.0,"y":734.2,"e":"Position"},{"t":292,"x":216.0,"y":710.1,"e":"Position"},{"t":297,"x":235.4,"y":689.8,"e":"Position"},{"t":302,"x":261.4,"y":691.6,"e":"Position"},{"t":307,"x":277.7,"y":672.1,"e":"Position"},{"t":312,"x":292.9,"y":647.9,"e":"Position"},{"t":317,"x":304.3,"y":614.9,"e":"Position"},{"t":322,"x":312.0,"y":592.9,"e":"Position"},{"t":327,"x":343.5,"y":606.8,"e":"Position"},{"t":332,"x":363.3,"y":601.0,"e":"Position"},{"t":337,"x":396.4,"y":601.3,"e":"Position"},{"t":339,"x":400.3,"y":600.5,"e":"Loot"},{"t":339,"x":400.3,"y":600.5,"e":"Loot"},{"t":339,"x":400.3,"y":600.5,"e":"Loot"},{"t":342,"x":396.6,"y":588.7,"e":"Position"},{"t":343,"x":396.6,"y":588.7,"e":"Loot"},{"t":343,"x":396.6,"y":588.7,"e":"Loot"},{"t":352,"x":402.1,"y":600.0,"e":"Position"},{"t":357,"x":427.9,"y":607.0,"e":"Position"},{"t":362,"x":451.6,"y":585.5,"e":"Position"},{"t":367,"x":456.0,"y":553.9,"e":"Position"},{"t":372,"x":457.1,"y":526.1,"e":"Position"},{"t":378,"x":454.4,"y":529.7,"e":"Position"},{"t":383,"x":456.8,"y":526.7,"e":"Position"},{"t":393,"x":460.6,"y":506.1,"e":"Position"},{"t":398,"x":443.3,"y":489.4,"e":"Position"},{"t":398,"x":443.3,"y":489.4,"e":"Loot"},{"t":398,"x":443.3,"y":489.4,"e":"Loot"},{"t":398,"x":443.3,"y":489.4,"e":"Loot"},{"t":403,"x":424.6,"y":490.2,"e":"Position"},{"t":408,"x":421.5,"y":493.4,"e":"Position"},{"t":409,"x":421.5,"y":493.4,"e":"Loot"},{"t":413,"x":420.8,"y":490.3,"e":"Position"},{"t":423,"x":438.0,"y":462.1,"e":"Position"},{"t":428,"x":458.6,"y":444.9,"e":"Position"},{"t":433,"x":487.1,"y":425.4,"e":"Position"},{"t":438,"x":513.4,"y":403.0,"e":"Position"},{"t":443,"x":531.1,"y":392.7,"e":"Position"},{"t":448,"x":543.5,"y":386.5,"e":"Position"},{"t":453,"x":538.1,"y":369.9,"e":"Position"},{"t":458,"x":543.9,"y":346.4,"e":"Position"},{"t":463,"x":572.8,"y":327.5,"e":"Position"},{"t":468,"x":600.8,"y":323.0,"e":"Position"},{"t":473,"x":603.2,"y":320.6,"e":"Position"},{"t":478,"x":623.4,"y":320.2,"e":"Position"},{"t":483,"x":653.1,"y":325.8,"e":"Position"},{"t":488,"x":666.1,"y":320.4,"e":"Position"},{"t":493,"x":668.2,"y":314.0,"e":"Position"},{"t":498,"x":677.4,"y":318.1,"e":"Position"},{"t":503,"x":685.8,"y":350.2,"e":"Position"},{"t":508,"x":687.5,"y":359.5,"e":"Position"},{"t":523,"x":714.2,"y":374.4,"e":"Position"},{"t":528,"x":706.1,"y":392.1,"e":"Position"},{"t":533,"x":691.0,"y":420.7,"e":"Position"},{"t":538,"x":689.1,"y":429.1,"e":"Position"},{"t":543,"x":665.4,"y":451.0,"e":"Position"},{"t":548,"x":632.3,"y":460.6,"e":"Position"},{"t":553,"x":627.5,"y":460.4,"e":"Position"},{"t":563,"x":627.5,"y":460.4,"e":"Loot"},{"t":574,"x":609.3,"y":442.6,"e":"Position"},{"t":579,"x":607.4,"y":429.0,"e":"Position"},{"t":589,"x":609.1,"y":428.0,"e":"Position"},{"t":594,"x":606.4,"y":429.6,"e":"Position"},{"t":604,"x":611.1,"y":435.0,"e":"Position"},{"t":609,"x":609.8,"y":434.5,"e":"Position"},{"t":614,"x":612.7,"y":434.8,"e":"Position"},{"t":619,"x":613.7,"y":433.9,"e":"Position"},{"t":625,"x":613.7,"y":433.9,"e":"BotKill"},{"t":629,"x":603.9,"y":430.4,"e":"Position"},{"t":632,"x":589.5,"y":420.0,"e":"Loot"},{"t":634,"x":587.8,"y":417.1,"e":"Position"},{"t":639,"x":609.1,"y":398.7,"e":"Position"},{"t":643,"x":624.4,"y":399.7,"e":"Loot"},{"t":644,"x":624.4,"y":399.7,"e":"Position"},{"t":646,"x":627.3,"y":396.2,"e":"Loot"},{"t":649,"x":622.3,"y":394.5,"e":"Position"},{"t":651,"x":613.2,"y":397.4,"e":"Loot"},{"t":654,"x":609.8,"y":396.3,"e":"Position"},{"t":664,"x":621.0,"y":407.2,"e":"Position"},{"t":669,"x":619.4,"y":401.9,"e":"Position"},{"t":674,"x":638.2,"y":389.4,"e":"Position"},{"t":679,"x":650.9,"y":383.0,"e":"Position"},{"t":684,"x":655.2,"y":369.4,"e":"Position"},{"t":689,"x":669.0,"y":338.6,"e":"Position"},{"t":694,"x":678.2,"y":305.3,"e":"Position"},{"t":699,"x":670.7,"y":274.8,"e":"Position"}]}}}