{"match_id":"5a3525ac-b9ae-4467-bc55-60d4fa05e9a9","map_id":"AmbroseValley","date":"February_10","duration_ms":171,"human_count":1,"bot_count":0,"players":{"070cc1c5-677f-4397-892b-70b4b77d3eab":{"is_bot":false,"events":[{"t":0,"x":223.0,"y":106.3,"e":"Position"},{"t":36,"x":225.4,"y":122.4,"e":"Position"},{"t":41,"x":241.0,"y":144.3,"e":"Position"},{"t":44,"x":238.6,"y":148.9,"e":"Loot"},{"t":45,"x":238.5,"y":148.7,"e":"Loot"},{"t":46,"x":238.5,"y":148.7,"e":"Position"},{"t":51,"x":243.0,"y":145.5,"e":"Position"},{"t":52,"x":243.0,"y":145.5,"e":"Loot"},{"t":56,"x":249.7,"y":148.8,"e":"Position"},{"t":61,"x":250.6,"y":133.6,"e":"Position"},{"t":66,"x":247.2,"y":141.2,"e":"Position"},{"t":67,"x":247.2,"y":141.2,"e":"Loot"},{"t":68,"x":247.2,"y":141.2,"e":"Loot"},{"t":71,"x":231.1,"y":142.4,"e":"Position"},{"t":76,"x":222.4,"y":147.9,"e":"Position"},{"t":86,"x":214.7,"y":171.0,"e":"Position"},{"t":91,"x":235.0,"y":186.0,"e":"Position"},{"t":96,"x":266.4,"y":198.6,"e":"Position"},{"t":101,"x":278.8,"y":201.3,"e":"Position"},{"t":106,"x":287.2,"y":205.8,"e":"Position"},{"t":111,"x":288.2,"y":213.1,"e":"Position"},{"t":116,"x":317.7,"y":210.8,"e":"Position"},{"t":121,"x":337.5,"y":199.6,"e":"Position"},{"t":126,"x":348.5,"y":199.7,"e":"Position"},{"t":131,"x":369.1,"y":194.9,"e":"Position"},{"t":136,"x":383.5,"y":197.2,"e":"Position"},{"t":138,"x":383.2,"y":197.1,"e":"Loot"},{"t":141,"x":387.8,"y":192.3,"e":"Position"},{"t":146,"x":419.5,"y":205.9,"e":"Position"},{"t":151,"x":444.3,"y":215.4,"e":"Position"},{"t":156,"x":452.2,"y":218.6,"e":"Position"},{"t":166,"x":450.1,"y":217.8,"e":"Position"},{"t":171,"x":451.8,"y":217.0,"e":"BotKilled"}]}}}