{"match_id":"d1ce8b10-7e32-46bc-87a9-5d2a9b6cdd35","map_id":"AmbroseValley","date":"February_10","duration_ms":281,"human_count":1,"bot_count":0,"players":{"a1d360c0-00b5-4622-a137-a9e099c0de46":{"is_bot":false,"events":[{"t":0,"x":303.0,"y":902.3,"e":"Position"},{"t":15,"x":310.5,"y":897.4,"e":"Position"},{"t":20,"x":339.0,"y":893.1,"e":"Position"},{"t":25,"x":352.7,"y":892.4,"e":"Position"},{"t":30,"x":361.0,"y":893.0,"e":"Position"},{"t":31,"x":361.6,"y":895.5,"e":"Loot"},{"t":37,"x":360.9,"y":892.4,"e":"Loot"},{"t":45,"x":361.5,"y":889.7,"e":"Position"},{"t":50,"x":353.6,"y":883.5,"e":"Position"},{"t":55,"x":356.0,"y":885.0,"e":"Position"},{"t":60,"x":355.0,"y":883.7,"e":"Position"},{"t":60,"x":355.0,"y":883.7,"e":"Loot"},{"t":62,"x":354.6,"y":883.4,"e":"Loot"},{"t":70,"x":365.0,"y":881.2,"e":"Position"},{"t":72,"x":365.0,"y":881.2,"e":"Loot"},{"t":75,"x":370.3,"y":891.4,"e":"Position"},{"t":77,"x":374.5,"y":894.8,"e":"Loot"},{"t":79,"x":372.5,"y":894.7,"e":"Loot"},{"t":85,"x":372.0,"y":889.0,"e":"Position"},{"t":90,"x":376.4,"y":890.5,"e":"Position"},{"t":95,"x":370.1,"y":892.5,"e":"Position"},{"t":100,"x":380.0,"y":902.3,"e":"Position"},{"t":105,"x":382.5,"y":897.7,"e":"Position"},{"t":109,"x":381.6,"y":894.8,"e":"Loot"},{"t":110,"x":381.4,"y":891.4,"e":"Position"},{"t":115,"x":378.7,"y":868.4,"e":"Position"},{"t":120,"x":398.4,"y":863.3,"e":"Position"},{"t":125,"x":400.9,"y":846.5,"e":"Position"},{"t":130,"x":404.6,"y":823.5,"e":"Position"},{"t":136,"x":401.8,"y":823.4,"e":"Position"},{"t":136,"x":401.8,"y":823.4,"e":"Loot"},{"t":141,"x":405.4,"y":815.0,"e":"Position"},{"t":143,"x":404.7,"y":815.4,"e":"Loot"},{"t":146,"x":415.0,"y":817.4,"e":"Position"},{"t":151,"x":412.7,"y":815.3,"e":"Position"},{"t":157,"x":413.8,"y":811.4,"e":"Loot"},{"t":161,"x":416.0,"y":804.9,"e":"Position"},{"t":162,"x":420.3,"y":800.9,"e":"Loot"},{"t":166,"x":416.7,"y":799.5,"e":"Position"},{"t":166,"x":416.0,"y":799.7,"e":"Loot"},{"t":171,"x":410.2,"y":803.1,"e":"Position"},{"t":173,"x":407.8,"y":797.5,"e":"Loot"},{"t":176,"x":410.6,"y":807.8,"e":"Position"},{"t":186,"x":405.9,"y":804.2,"e":"Position"},{"t":187,"x":406.2,"y":804.9,"e":"Loot"},{"t":191,"x":412.1,"y":807.2,"e":"Position"},{"t":195,"x":412.7,"y":799.5,"e":"Loot"},{"t":196,"x":413.7,"y":799.7,"e":"Position"},{"t":201,"x":408.5,"y":797.5,"e":"Position"},{"t":206,"x":401.7,"y":807.1,"e":"Position"},{"t":209,"x":400.4,"y":803.6,"e":"Loot"},{"t":211,"x":401.1,"y":800.4,"e":"Position"},{"t":216,"x":405.8,"y":793.5,"e":"Position"},{"t":221,"x":412.7,"y":809.2,"e":"Position"},{"t":226,"x":413.5,"y":814.1,"e":"Position"},{"t":231,"x":422.4,"y":814.4,"e":"Position"},{"t":236,"x":409.9,"y":824.4,"e":"Position"},{"t":241,"x":384.8,"y":828.0,"e":"Position"},{"t":246,"x":357.0,"y":813.5,"e":"Position"},{"t":251,"x":326.2,"y":811.0,"e":"Position"},{"t":256,"x":308.9,"y":796.3,"e":"Position"},{"t":261,"x":302.0,"y":799.1,"e":"Loot"},{"t":261,"x":302.0,"y":799.1,"e":"Position"},{"t":266,"x":289.0,"y":772.9,"e":"Position"},{"t":271,"x":262.7,"y":776.2,"e":"Position"},{"t":276,"x":247.9,"y":767.8,"e":"Position"},{"t":281,"x":252.1,"y":766.1,"e":"Position"}]}}}