{"match_id":"6840599c-3c11-4c09-8b1e-f9023a881a58","map_id":"AmbroseValley","date":"February_10","duration_ms":101,"human_count":1,"bot_count":0,"players":{"1b44d5cd-65b3-4e09-a18f-c342612ae720":{"is_bot":false,"events":[{"t":0,"x":77.5,"y":884.3,"e":"Position"},{"t":15,"x":84.5,"y":883.0,"e":"Position"},{"t":20,"x":110.4,"y":876.9,"e":"Position"},{"t":25,"x":132.8,"y":870.1,"e":"Position"},{"t":30,"x":153.6,"y":856.6,"e":"Position"},{"t":35,"x":175.7,"y":846.4,"e":"Position"},{"t":40,"x":179.1,"y":853.3,"e":"Position"},{"t":45,"x":168.8,"y":852.4,"e":"Position"},{"t":49,"x":168.2,"y":851.7,"e":"Loot"},{"t":56,"x":174.1,"y":862.4,"e":"Position"},{"t":60,"x":175.5,"y":862.0,"e":"BotKill"},{"t":66,"x":191.2,"y":859.0,"e":"Position"},{"t":70,"x":204.4,"y":855.9,"e":"Loot"},{"t":70,"x":204.4,"y":855.9,"e":"Loot"},{"t":71,"x":204.4,"y":855.9,"e":"Position"},{"t":76,"x":228.8,"y":854.7,"e":"Position"},{"t":81,"x":230.5,"y":860.6,"e":"Position"},{"t":82,"x":230.5,"y":860.6,"e":"Loot"},{"t":82,"x":230.5,"y":860.6,"e":"Loot"},{"t":86,"x":231.0,"y":854.7,"e":"Position"},{"t":91,"x":225.0,"y":850.2,"e":"Position"},{"t":98,"x":226.4,"y":849.7,"e":"BotKilled"},{"t":101,"x":226.4,"y":849.5,"e":"Position"}]}}}