{"match_id":"a81cca92-3c23-40ff-b67a-84b782c060f5","map_id":"AmbroseValley","date":"February_11","duration_ms":285,"human_count":0,"bot_count":7,"players":{"1429":{"is_bot":true,"events":[{"t":0,"x":726.9,"y":540.5,"e":"Position"},{"t":20,"x":721.3,"y":541.5,"e":"Position"},{"t":25,"x":709.5,"y":540.7,"e":"Position"},{"t":32,"x":709.2,"y":539.6,"e":"Loot"},{"t":35,"x":713.6,"y":540.6,"e":"Position"},{"t":40,"x":701.4,"y":540.1,"e":"Position"},{"t":44,"x":695.5,"y":537.9,"e":"Loot"},{"t":44,"x":695.5,"y":537.9,"e":"Loot"},{"t":44,"x":695.5,"y":537.9,"e":"Loot"},{"t":45,"x":695.5,"y":537.9,"e":"Position"},{"t":50,"x":694.7,"y":531.8,"e":"Position"},{"t":55,"x":686.7,"y":525.3,"e":"Position"},{"t":60,"x":688.8,"y":518.3,"e":"Position"},{"t":65,"x":688.0,"y":518.2,"e":"Position"},{"t":75,"x":685.7,"y":526.6,"e":"Position"},{"t":80,"x":686.1,"y":546.4,"e":"Position"},{"t":85,"x":682.0,"y":553.4,"e":"Position"},{"t":90,"x":686.0,"y":564.7,"e":"Position"},{"t":95,"x":689.7,"y":564.9,"e":"Position"},{"t":100,"x":684.7,"y":569.9,"e":"Position"},{"t":105,"x":678.6,"y":587.7,"e":"Position"},{"t":110,"x":669.6,"y":599.8,"e":"Position"},{"t":115,"x":667.8,"y":604.8,"e":"Loot"},{"t":131,"x":663.7,"y":601.2,"e":"Position"},{"t":136,"x":674.6,"y":602.4,"e":"Position"},{"t":141,"x":679.6,"y":619.3,"e":"Position"},{"t":146,"x":677.0,"y":640.2,"e":"Position"},{"t":151,"x":674.3,"y":655.7,"e":"Position"},{"t":156,"x":669.5,"y":665.2,"e":"Position"},{"t":178,"x":669.9,"y":669.6,"e":"Position"},{"t":184,"x":678.2,"y":670.8,"e":"Position"}]},"1433":{"is_bot":true,"events":[{"t":5,"x":106.4,"y":849.5,"e":"BotPosition"},{"t":10,"x":125.4,"y":831.3,"e":"BotPosition"},{"t":15,"x":143.2,"y":815.5,"e":"BotPosition"},{"t":20,"x":154.8,"y":797.3,"e":"BotPosition"},{"t":25,"x":168.4,"y":785.0,"e":"BotPosition"},{"t":30,"x":179.3,"y":773.7,"e":"BotPosition"},{"t":35,"x":187.6,"y":754.2,"e":"BotPosition"},{"t":40,"x":191.7,"y":751.7,"e":"BotPosition"},{"t":60,"x":206.3,"y":750.4,"e":"BotPosition"},{"t":65,"x":224.6,"y":749.5,"e":"BotPosition"},{"t":70,"x":241.6,"y":745.7,"e":"BotPosition"},{"t":75,"x":245.1,"y":730.0,"e":"BotPosition"},{"t":80,"x":249.6,"y":715.0,"e":"BotPosition"},{"t":85,"x":268.1,"y":696.2,"e":"BotPosition"},{"t":90,"x":282.4,"y":681.2,"e":"BotPosition"},{"t":95,"x":300.2,"y":666.9,"e":"BotPosition"},{"t":100,"x":311.7,"y":656.6,"e":"BotPosition"},{"t":105,"x":320.6,"y":643.4,"e":"BotPosition"},{"t":110,"x":325.6,"y":634.1,"e":"BotPosition"},{"t":116,"x":332.0,"y":609.3,"e":"BotPosition"},{"t":121,"x":341.3,"y":587.0,"e":"BotPosition"},{"t":125,"x":342.8,"y":592.9,"e":"BotKill"},{"t":126,"x":342.2,"y":593.2,"e":"BotPosition"},{"t":131,"x":351.6,"y":575.8,"e":"BotPosition"},{"t":136,"x":372.6,"y":558.6,"e":"BotPosition"},{"t":141,"x":383.4,"y":563.2,"e":"BotPosition"},{"t":146,"x":390.4,"y":580.1,"e":"BotPosition"},{"t":151,"x":393.3,"y":554.1,"e":"BotPosition"},{"t":156,"x":406.7,"y":549.5,"e":"BotPosition"},{"t":161,"x":393.3,"y":564.1,"e":"BotPosition"},{"t":166,"x":396.2,"y":549.9,"e":"BotPosition"},{"t":171,"x":407.6,"y":525.4,"e":"BotPosition"},{"t":178,"x":417.9,"y":499.9,"e":"BotPosition"},{"t":184,"x":417.2,"y":506.2,"e":"BotPosition"},{"t":190,"x":416.3,"y":494.2,"e":"BotPosition"},{"t":195,"x":401.3,"y":484.8,"e":"BotPosition"},{"t":200,"x":382.2,"y":479.7,"e":"BotPosition"},{"t":205,"x":404.3,"y":483.2,"e":"BotPosition"},{"t":210,"x":412.5,"y":484.4,"e":"BotPosition"},{"t":215,"x":419.4,"y":483.9,"e":"BotPosition"},{"t":220,"x":420.0,"y":467.3,"e":"BotPosition"},{"t":225,"x":430.7,"y":474.7,"e":"BotPosition"},{"t":230,"x":423.6,"y":469.1,"e":"BotPosition"},{"t":235,"x":441.7,"y":480.4,"e":"BotPosition"},{"t":240,"x":437.6,"y":466.3,"e":"BotPosition"},{"t":245,"x":420.5,"y":479.3,"e":"BotPosition"},{"t":250,"x":403.4,"y":498.1,"e":"BotPosition"},{"t":255,"x":386.2,"y":515.4,"e":"BotPosition"},{"t":260,"x":376.0,"y":538.0,"e":"BotPosition"},{"t":265,"x":366.6,"y":525.2,"e":"BotPosition"},{"t":270,"x":356.4,"y":525.1,"e":"BotPosition"},{"t":275,"x":359.2,"y":509.3,"e":"BotPosition"},{"t":280,"x":359.2,"y":497.3,"e":"BotPosition"},{"t":285,"x":349.5,"y":486.9,"e":"BotPosition"}]},"1437":{"is_bot":true,"events":[{"t":5,"x":675.3,"y":250.2,"e":"BotPosition"},{"t":10,"x":661.2,"y":267.7,"e":"BotPosition"},{"t":15,"x":644.4,"y":288.3,"e":"BotPosition"},{"t":20,"x":625.8,"y":307.4,"e":"BotPosition"},{"t":25,"x":610.6,"y":327.1,"e":"BotPosition"},{"t":30,"x":591.6,"y":338.8,"e":"BotPosition"},{"t":35,"x":568.4,"y":353.8,"e":"BotPosition"},{"t":40,"x":549.4,"y":366.0,"e":"BotPosition"},{"t":45,"x":533.0,"y":386.8,"e":"BotPosition"},{"t":50,"x":516.6,"y":405.6,"e":"BotPosition"},{"t":55,"x":505.7,"y":418.1,"e":"BotPosition"},{"t":60,"x":494.3,"y":440.7,"e":"BotPosition"},{"t":65,"x":473.6,"y":458.5,"e":"BotPosition"},{"t":70,"x":454.7,"y":468.8,"e":"BotPosition"},{"t":75,"x":451.7,"y":474.6,"e":"BotPosition"},{"t":80,"x":430.9,"y":482.8,"e":"BotPosition"},{"t":85,"x":412.8,"y":490.0,"e":"BotPosition"},{"t":90,"x":419.4,"y":491.5,"e":"BotPosition"},{"t":91,"x":419.8,"y":491.7,"e":"BotKill"},{"t":95,"x":417.9,"y":472.4,"e":"BotPosition"},{"t":100,"x":434.9,"y":477.4,"e":"BotPosition"},{"t":105,"x":422.9,"y":486.0,"e":"BotPosition"},{"t":110,"x":406.8,"y":499.5,"e":"BotPosition"},{"t":116,"x":405.1,"y":497.1,"e":"BotPosition"},{"t":121,"x":423.4,"y":491.3,"e":"BotPosition"},{"t":125,"x":432.3,"y":498.5,"e":"BotKilled"}]},"1441":{"is_bot":true,"events":[{"t":5,"x":302.9,"y":882.3,"e":"BotPosition"},{"t":10,"x":319.3,"y":873.9,"e":"BotPosition"},{"t":15,"x":347.3,"y":876.2,"e":"BotPosition"},{"t":20,"x":366.3,"y":881.8,"e":"BotPosition"},{"t":25,"x":381.3,"y":891.1,"e":"BotPosition"},{"t":35,"x":388.9,"y":866.1,"e":"BotPosition"},{"t":40,"x":392.3,"y":840.9,"e":"BotPosition"},{"t":45,"x":407.9,"y":821.4,"e":"BotPosition"},{"t":50,"x":412.0,"y":811.6,"e":"BotPosition"},{"t":55,"x":409.9,"y":832.7,"e":"BotPosition"},{"t":60,"x":404.8,"y":847.7,"e":"BotPosition"},{"t":65,"x":417.6,"y":825.7,"e":"BotPosition"},{"t":70,"x":432.2,"y":809.9,"e":"BotPosition"},{"t":75,"x":410.5,"y":803.4,"e":"BotPosition"},{"t":80,"x":406.0,"y":806.3,"e":"BotPosition"},{"t":85,"x":406.5,"y":789.7,"e":"BotPosition"},{"t":90,"x":391.9,"y":765.8,"e":"BotPosition"},{"t":95,"x":390.1,"y":740.0,"e":"BotPosition"},{"t":100,"x":395.9,"y":714.3,"e":"BotPosition"},{"t":105,"x":420.8,"y":709.5,"e":"BotPosition"},{"t":110,"x":448.5,"y":706.0,"e":"BotPosition"},{"t":116,"x":451.8,"y":724.9,"e":"BotPosition"},{"t":121,"x":445.4,"y":748.5,"e":"BotPosition"},{"t":122,"x":442.7,"y":753.3,"e":"BotKill"},{"t":126,"x":435.5,"y":750.1,"e":"BotPosition"},{"t":131,"x":433.5,"y":746.7,"e":"BotPosition"},{"t":136,"x":461.5,"y":748.3,"e":"BotPosition"},{"t":141,"x":484.9,"y":755.1,"e":"BotPosition"},{"t":146,"x":462.5,"y":770.0,"e":"BotPosition"},{"t":151,"x":449.6,"y":791.6,"e":"BotPosition"},{"t":156,"x":459.9,"y":809.7,"e":"BotPosition"},{"t":161,"x":447.2,"y":806.8,"e":"BotPosition"},{"t":166,"x":435.8,"y":804.8,"e":"BotPosition"},{"t":171,"x":446.4,"y":826.9,"e":"BotPosition"},{"t":178,"x":463.2,"y":833.1,"e":"BotPosition"},{"t":184,"x":455.3,"y":830.8,"e":"BotPosition"},{"t":190,"x":455.1,"y":808.3,"e":"BotPosition"},{"t":195,"x":448.2,"y":784.1,"e":"BotPosition"},{"t":200,"x":444.2,"y":761.2,"e":"BotPosition"},{"t":205,"x":428.3,"y":768.0,"e":"BotPosition"},{"t":210,"x":408.9,"y":785.8,"e":"BotPosition"},{"t":215,"x":399.6,"y":768.1,"e":"BotPosition"},{"t":220,"x":396.9,"y":751.6,"e":"BotPosition"},{"t":225,"x":397.3,"y":729.1,"e":"BotPosition"},{"t":230,"x":403.6,"y":710.6,"e":"BotPosition"},{"t":235,"x":415.0,"y":685.5,"e":"BotPosition"},{"t":240,"x":425.4,"y":659.4,"e":"BotPosition"},{"t":245,"x":435.9,"y":633.4,"e":"BotPosition"},{"t":250,"x":419.3,"y":645.2,"e":"BotPosition"},{"t":255,"x":418.9,"y":667.2,"e":"BotPosition"},{"t":260,"x":416.6,"y":674.8,"e":"BotPosition"},{"t":265,"x":409.2,"y":687.1,"e":"BotPosition"},{"t":270,"x":405.3,"y":696.7,"e":"BotPosition"},{"t":275,"x":405.5,"y":692.8,"e":"BotPosition"},{"t":280,"x":406.9,"y":666.5,"e":"BotPosition"},{"t":285,"x":409.9,"y":638.8,"e":"BotPosition"}]},"1445":{"is_bot":true,"events":[{"t":5,"x":226.2,"y":130.1,"e":"BotPosition"},{"t":10,"x":214.4,"y":149.6,"e":"BotPosition"},{"t":15,"x":205.3,"y":172.5,"e":"BotPosition"},{"t":20,"x":208.1,"y":175.9,"e":"BotPosition"},{"t":25,"x":209.8,"y":163.4,"e":"BotPosition"},{"t":30,"x":210.1,"y":157.6,"e":"BotPosition"},{"t":35,"x":208.6,"y":179.7,"e":"BotPosition"},{"t":40,"x":199.5,"y":203.9,"e":"BotPosition"},{"t":45,"x":201.6,"y":228.8,"e":"BotPosition"},{"t":50,"x":211.6,"y":221.3,"e":"BotPosition"},{"t":55,"x":213.6,"y":239.4,"e":"BotPosition"},{"t":60,"x":225.2,"y":257.6,"e":"BotPosition"},{"t":65,"x":234.3,"y":278.3,"e":"BotPosition"},{"t":70,"x":233.9,"y":299.1,"e":"BotPosition"},{"t":75,"x":218.7,"y":318.9,"e":"BotPosition"},{"t":80,"x":209.2,"y":340.2,"e":"BotPosition"},{"t":85,"x":216.4,"y":365.6,"e":"BotPosition"},{"t":90,"x":227.9,"y":391.2,"e":"BotPosition"},{"t":95,"x":246.9,"y":408.1,"e":"BotPosition"},{"t":100,"x":263.2,"y":420.7,"e":"BotPosition"},{"t":105,"x":263.3,"y":397.0,"e":"BotPosition"},{"t":110,"x":267.9,"y":390.0,"e":"BotPosition"},{"t":116,"x":267.9,"y":396.7,"e":"BotPosition"},{"t":121,"x":266.0,"y":404.5,"e":"BotPosition"},{"t":126,"x":265.7,"y":409.2,"e":"BotPosition"},{"t":131,"x":278.0,"y":420.4,"e":"BotPosition"},{"t":136,"x":286.3,"y":418.8,"e":"BotPosition"},{"t":141,"x":295.6,"y":408.2,"e":"BotPosition"},{"t":146,"x":295.8,"y":407.6,"e":"BotPosition"},{"t":151,"x":286.5,"y":410.1,"e":"BotPosition"},{"t":156,"x":282.9,"y":422.8,"e":"BotPosition"},{"t":161,"x":285.6,"y":417.9,"e":"BotPosition"},{"t":166,"x":288.9,"y":395.7,"e":"BotPosition"},{"t":171,"x":295.5,"y":394.6,"e":"BotPosition"},{"t":182,"x":291.9,"y":403.5,"e":"BotKill"},{"t":184,"x":291.5,"y":415.3,"e":"BotPosition"},{"t":190,"x":285.1,"y":419.1,"e":"BotPosition"},{"t":195,"x":277.8,"y":427.2,"e":"BotPosition"},{"t":200,"x":278.0,"y":431.9,"e":"BotPosition"},{"t":210,"x":281.1,"y":438.0,"e":"BotPosition"},{"t":215,"x":285.8,"y":436.5,"e":"BotPosition"},{"t":220,"x":281.3,"y":417.7,"e":"BotPosition"},{"t":230,"x":287.4,"y":423.8,"e":"BotPosition"},{"t":235,"x":287.5,"y":437.4,"e":"BotPosition"},{"t":240,"x":287.3,"y":433.5,"e":"BotPosition"},{"t":245,"x":286.8,"y":424.9,"e":"BotPosition"},{"t":250,"x":288.9,"y":419.7,"e":"BotPosition"},{"t":255,"x":288.5,"y":428.3,"e":"BotPosition"},{"t":260,"x":288.8,"y":431.5,"e":"BotPosition"},{"t":265,"x":291.0,"y":423.1,"e":"BotPosition"},{"t":270,"x":293.1,"y":423.4,"e":"BotPosition"},{"t":280,"x":292.0,"y":436.2,"e":"BotPosition"},{"t":285,"x":289.0,"y":451.0,"e":"BotPosition"}]},"1449":{"is_bot":true,"events":[{"t":5,"x":275.7,"y":699.2,"e":"BotPosition"},{"t":10,"x":279.8,"y":687.9,"e":"BotPosition"},{"t":15,"x":267.3,"y":678.7,"e":"BotPosition"},{"t":20,"x":288.8,"y":675.4,"e":"BotPosition"},{"t":25,"x":306.7,"y":681.4,"e":"BotPosition"},{"t":30,"x":309.9,"y":684.9,"e":"BotPosition"},{"t":35,"x":292.6,"y":686.1,"e":"BotPosition"},{"t":40,"x":280.6,"y":690.8,"e":"BotPosition"},{"t":45,"x":297.7,"y":684.9,"e":"BotPosition"},{"t":50,"x":313.3,"y":681.4,"e":"BotPosition"},{"t":55,"x":324.2,"y":669.7,"e":"BotPosition"},{"t":60,"x":332.0,"y":654.2,"e":"BotPosition"},{"t":65,"x":356.5,"y":643.6,"e":"BotPosition"},{"t":70,"x":376.5,"y":632.4,"e":"BotPosition"},{"t":75,"x":373.9,"y":611.4,"e":"BotPosition"},{"t":80,"x":385.9,"y":605.6,"e":"BotPosition"},{"t":85,"x":400.8,"y":603.3,"e":"BotPosition"},{"t":90,"x":418.1,"y":594.3,"e":"BotPosition"},{"t":95,"x":436.8,"y":596.0,"e":"BotPosition"},{"t":100,"x":428.0,"y":572.4,"e":"BotPosition"},{"t":105,"x":425.4,"y":545.4,"e":"BotPosition"},{"t":110,"x":447.2,"y":557.5,"e":"BotPosition"},{"t":116,"x":473.0,"y":568.2,"e":"BotPosition"},{"t":121,"x":453.3,"y":560.7,"e":"BotPosition"},{"t":126,"x":430.0,"y":548.3,"e":"BotPosition"},{"t":131,"x":431.5,"y":534.2,"e":"BotPosition"},{"t":132,"x":432.8,"y":531.8,"e":"BotKill"},{"t":136,"x":433.7,"y":523.7,"e":"BotPosition"},{"t":141,"x":433.7,"y":515.7,"e":"BotPosition"},{"t":143,"x":429.9,"y":509.4,"e":"BotKill"},{"t":146,"x":426.7,"y":509.8,"e":"BotPosition"},{"t":156,"x":434.2,"y":506.1,"e":"BotPosition"},{"t":161,"x":446.1,"y":499.0,"e":"BotPosition"},{"t":166,"x":420.1,"y":489.8,"e":"BotPosition"},{"t":171,"x":399.6,"y":494.3,"e":"BotPosition"},{"t":178,"x":400.0,"y":491.2,"e":"BotPosition"},{"t":184,"x":417.4,"y":489.2,"e":"BotPosition"},{"t":190,"x":435.1,"y":502.0,"e":"BotPosition"},{"t":195,"x":422.3,"y":510.3,"e":"BotPosition"},{"t":200,"x":422.5,"y":497.5,"e":"BotPosition"},{"t":205,"x":426.4,"y":481.7,"e":"BotPosition"},{"t":210,"x":414.7,"y":484.3,"e":"BotPosition"},{"t":215,"x":420.3,"y":474.5,"e":"BotPosition"},{"t":220,"x":409.6,"y":459.0,"e":"BotPosition"},{"t":225,"x":419.7,"y":468.3,"e":"BotPosition"},{"t":230,"x":423.3,"y":484.7,"e":"BotPosition"},{"t":235,"x":419.1,"y":488.9,"e":"BotPosition"},{"t":240,"x":419.3,"y":483.4,"e":"BotPosition"},{"t":245,"x":428.2,"y":476.1,"e":"BotPosition"},{"t":250,"x":423.3,"y":469.7,"e":"BotPosition"},{"t":255,"x":437.2,"y":474.6,"e":"BotPosition"},{"t":260,"x":438.5,"y":495.0,"e":"BotPosition"},{"t":265,"x":423.8,"y":488.7,"e":"BotPosition"},{"t":270,"x":438.4,"y":496.4,"e":"BotPosition"},{"t":273,"x":437.4,"y":495.4,"e":"BotKilled"}]},"1453":{"is_bot":true,"events":[{"t":5,"x":77.3,"y":469.8,"e":"BotPosition"},{"t":10,"x":99.7,"y":463.7,"e":"BotPosition"},{"t":15,"x":127.2,"y":465.5,"e":"BotPosition"},{"t":20,"x":144.2,"y":455.2,"e":"BotPosition"},{"t":25,"x":163.7,"y":440.5,"e":"BotPosition"},{"t":30,"x":190.5,"y":433.1,"e":"BotPosition"},{"t":35,"x":214.3,"y":423.3,"e":"BotPosition"},{"t":40,"x":238.9,"y":418.9,"e":"BotPosition"},{"t":45,"x":266.8,"y":416.0,"e":"BotPosition"},{"t":50,"x":293.0,"y":419.4,"e":"BotPosition"},{"t":55,"x":295.4,"y":424.8,"e":"BotPosition"},{"t":70,"x":291.7,"y":421.6,"e":"BotPosition"},{"t":80,"x":283.5,"y":442.2,"e":"BotPosition"},{"t":85,"x":286.8,"y":451.5,"e":"BotPosition"},{"t":90,"x":288.2,"y":458.0,"e":"BotPosition"},{"t":95,"x":283.1,"y":439.2,"e":"BotPosition"},{"t":105,"x":290.7,"y":423.4,"e":"BotPosition"},{"t":110,"x":284.2,"y":419.3,"e":"BotPosition"},{"t":116,"x":275.9,"y":433.2,"e":"BotPosition"},{"t":121,"x":282.8,"y":437.0,"e":"BotPosition"},{"t":126,"x":285.1,"y":452.8,"e":"BotPosition"},{"t":131,"x":287.6,"y":465.8,"e":"BotPosition"},{"t":136,"x":292.7,"y":451.4,"e":"BotPosition"},{"t":141,"x":301.7,"y":435.5,"e":"BotPosition"},{"t":146,"x":289.7,"y":437.3,"e":"BotPosition"},{"t":151,"x":286.2,"y":462.8,"e":"BotPosition"},{"t":156,"x":286.1,"y":452.6,"e":"BotPosition"},{"t":161,"x":282.7,"y":428.9,"e":"BotPosition"},{"t":166,"x":287.5,"y":440.6,"e":"BotPosition"},{"t":171,"x":288.3,"y":425.9,"e":"BotPosition"},{"t":178,"x":292.2,"y":401.2,"e":"BotPosition"},{"t":182,"x":293.2,"y":395.4,"e":"BotKilled"}]}}}