{"match_id":"275e5bc9-fe98-4616-a543-17d4277a1ca5","map_id":"GrandRift","date":"February_14","duration_ms":302,"human_count":1,"bot_count":0,"players":{"b15bb032-6782-441a-9bd8-b42d446220cd":{"is_bot":false,"events":[{"t":0,"x":366.8,"y":825.2,"e":"Position"},{"t":10,"x":371.5,"y":803.5,"e":"Position"},{"t":15,"x":364.9,"y":818.4,"e":"Position"},{"t":20,"x":357.6,"y":784.6,"e":"Position"},{"t":25,"x":347.2,"y":773.7,"e":"Position"},{"t":35,"x":316.1,"y":749.1,"e":"Position"},{"t":40,"x":309.6,"y":734.0,"e":"Position"},{"t":45,"x":325.6,"y":736.2,"e":"Position"},{"t":50,"x":349.1,"y":725.6,"e":"Position"},{"t":55,"x":358.7,"y":717.1,"e":"Position"},{"t":60,"x":365.0,"y":716.0,"e":"Position"},{"t":68,"x":360.2,"y":716.7,"e":"Loot"},{"t":70,"x":354.4,"y":698.9,"e":"Position"},{"t":75,"x":397.6,"y":716.4,"e":"Position"},{"t":80,"x":396.2,"y":711.2,"e":"Position"},{"t":85,"x":385.5,"y":686.0,"e":"Position"},{"t":90,"x":392.7,"y":652.5,"e":"Position"},{"t":95,"x":385.9,"y":691.1,"e":"Position"},{"t":100,"x":392.3,"y":667.9,"e":"Position"},{"t":105,"x":396.1,"y":626.8,"e":"Position"},{"t":110,"x":397.1,"y":599.9,"e":"Position"},{"t":115,"x":388.4,"y":575.9,"e":"Position"},{"t":121,"x":386.8,"y":571.1,"e":"Position"},{"t":123,"x":395.8,"y":588.6,"e":"BotKill"},{"t":125,"x":396.8,"y":589.9,"e":"Loot"},{"t":126,"x":396.8,"y":589.9,"e":"Position"},{"t":126,"x":396.8,"y":589.9,"e":"Loot"},{"t":127,"x":396.8,"y":589.9,"e":"Loot"},{"t":131,"x":393.3,"y":600.6,"e":"Position"},{"t":141,"x":399.8,"y":584.3,"e":"Position"},{"t":146,"x":393.9,"y":539.3,"e":"Position"},{"t":151,"x":378.6,"y":488.6,"e":"Position"},{"t":156,"x":375.9,"y":436.9,"e":"Position"},{"t":161,"x":404.2,"y":429.6,"e":"Position"},{"t":166,"x":421.9,"y":395.4,"e":"Position"},{"t":171,"x":425.5,"y":362.8,"e":"Position"},{"t":176,"x":415.1,"y":334.7,"e":"Position"},{"t":181,"x":420.0,"y":333.2,"e":"Loot"},{"t":182,"x":420.0,"y":333.2,"e":"Loot"},{"t":186,"x":417.4,"y":344.1,"e":"Position"},{"t":191,"x":431.0,"y":379.6,"e":"Position"},{"t":196,"x":476.4,"y":373.5,"e":"Position"},{"t":201,"x":497.3,"y":378.0,"e":"Position"},{"t":206,"x":497.4,"y":362.6,"e":"Position"},{"t":211,"x":497.9,"y":376.2,"e":"Position"},{"t":216,"x":505.1,"y":414.1,"e":"Position"},{"t":221,"x":510.7,"y":423.7,"e":"Position"},{"t":226,"x":505.7,"y":398.6,"e":"Position"},{"t":231,"x":501.3,"y":397.6,"e":"Position"},{"t":246,"x":512.6,"y":404.9,"e":"Position"},{"t":251,"x":501.1,"y":388.8,"e":"BotKill"},{"t":251,"x":501.3,"y":388.6,"e":"Position"},{"t":254,"x":502.7,"y":394.3,"e":"Loot"},{"t":256,"x":502.3,"y":394.8,"e":"Position"},{"t":261,"x":499.7,"y":397.5,"e":"Position"},{"t":271,"x":503.0,"y":396.7,"e":"Position"},{"t":276,"x":502.2,"y":395.6,"e":"Position"},{"t":281,"x":503.5,"y":393.6,"e":"Position"},{"t":291,"x":501.5,"y":392.1,"e":"Position"},{"t":297,"x":503.9,"y":391.2,"e":"Position"},{"t":302,"x":503.2,"y":385.3,"e":"Position"}]}}}